pypaymentsense
