Metadata-Version: 1.1
Name: pypaymentsense
Version: 0.2
Summary: Python libary for payment sense hosted forms
Home-page: https://github.com/crooksey/pyPaymentSense
Author: Luke Crooks
Author-email: luke@pumalo.org
License: MIT
Keywords: paymentsense payment sense
Platform: UNKNOWN
Classifier: Development Status :: 4 - Beta
Classifier: Intended Audience :: Developers
Classifier: License :: OSI Approved :: MIT License
Classifier: Programming Language :: Python :: 2.7
